llm_tools_readonly_fs/__init__.py
llm_tools_readonly_fs/llm_tools_readonly_fs.py
llm_tools_readonly_fs-0.1.0.dist-info/WHEEL
llm_tools_readonly_fs-0.1.0.dist-info/entry_points.txt
llm_tools_readonly_fs-0.1.0.dist-info/METADATA
llm_tools_readonly_fs-0.1.0.dist-info/RECORD
