Metadata-Version: 2.4
Name: llm-tools-readonly-fs
Version: 0.1.0
Summary: Grants LLM the ability to glob, grep, and view files within a directory
Author: Brett Harvey
License-Expression: MIT
Requires-Dist: llm>=0.26
Requires-Dist: readonly-fs-tools>=0.2.0
Requires-Python: >=3.9
Project-URL: CI, https://github.com/rbharvs/llm-tools-readonly-fs/actions
Project-URL: Changelog, https://github.com/rbharvs/llm-tools-readonly-fs/releases
Project-URL: Homepage, https://github.com/rbharvs/llm-tools-readonly-fs
Project-URL: Issues, https://github.com/rbharvs/llm-tools-readonly-fs/issues
